{"nodes": [{"id": "d_smart_reminder_system_backend_app_services_blob_storage_py", "label": "blob_storage.py", "file_type": "code", "source_file": "D:\\smart-reminder-system\\backend\\app\\services\\blob_storage.py", "source_location": "L1"}, {"id": "services_blob_storage_parse_conn_str", "label": "_parse_conn_str()", "file_type": "code", "source_file": "D:\\smart-reminder-system\\backend\\app\\services\\blob_storage.py", "source_location": "L14"}, {"id": "services_blob_storage_container_client", "label": "_container_client()", "file_type": "code", "source_file": "D:\\smart-reminder-system\\backend\\app\\services\\blob_storage.py", "source_location": "L24"}, {"id": "services_blob_storage_upload_audio", "label": "upload_audio()", "file_type": "code", "source_file": "D:\\smart-reminder-system\\backend\\app\\services\\blob_storage.py", "source_location": "L31"}, {"id": "services_blob_storage_generate_sas_url", "label": "generate_sas_url()", "file_type": "code", "source_file": "D:\\smart-reminder-system\\backend\\app\\services\\blob_storage.py", "source_location": "L41"}, {"id": "services_blob_storage_delete_audio", "label": "delete_audio()", "file_type": "code", "source_file": "D:\\smart-reminder-system\\backend\\app\\services\\blob_storage.py", "source_location": "L62"}, {"id": "services_blob_storage_copy_audio", "label": "copy_audio()", "file_type": "code", "source_file": "D:\\smart-reminder-system\\backend\\app\\services\\blob_storage.py", "source_location": "L69"}, {"id": "services_blob_storage_rationale_15", "label": "Split 'Key=Value;Key=Value' \u2014 partition on first '=' handles base64 values.", "file_type": "rationale", "source_file": "D:\\smart-reminder-system\\backend\\app\\services\\blob_storage.py", "source_location": "L15"}, {"id": "services_blob_storage_rationale_32", "label": "Upload bytes to private blob storage.", "file_type": "rationale", "source_file": "D:\\smart-reminder-system\\backend\\app\\services\\blob_storage.py", "source_location": "L32"}, {"id": "services_blob_storage_rationale_42", "label": "Return a time-limited SAS URL so Twilio can fetch a private audio blob.", "file_type": "rationale", "source_file": "D:\\smart-reminder-system\\backend\\app\\services\\blob_storage.py", "source_location": "L42"}, {"id": "services_blob_storage_rationale_70", "label": "Server-side copy within the same container.", "file_type": "rationale", "source_file": "D:\\smart-reminder-system\\backend\\app\\services\\blob_storage.py", "source_location": "L70"}], "edges": [{"source": "d_smart_reminder_system_backend_app_services_blob_storage_py", "target": "logging", "relation": "imports", "context": "import", "confidence": "EXTRACTED", "source_file": "D:\\smart-reminder-system\\backend\\app\\services\\blob_storage.py", "source_location": "L1", "weight": 1.0}, {"source": "d_smart_reminder_system_backend_app_services_blob_storage_py", "target": "datetime", "relation": "imports_from", "context": "import", "confidence": "EXTRACTED", "source_file": "D:\\smart-reminder-system\\backend\\app\\services\\blob_storage.py", "source_location": "L2", "weight": 1.0}, {"source": "d_smart_reminder_system_backend_app_services_blob_storage_py", "target": "azure_storage_blob", "relation": "imports_from", "context": "import", "confidence": "EXTRACTED", "source_file": "D:\\smart-reminder-system\\backend\\app\\services\\blob_storage.py", "source_location": "L3", "weight": 1.0}, {"source": "d_smart_reminder_system_backend_app_services_blob_storage_py", "target": "app_config", "relation": "imports_from", "context": "import", "confidence": "EXTRACTED", "source_file": "D:\\smart-reminder-system\\backend\\app\\services\\blob_storage.py", "source_location": "L9", "weight": 1.0}, {"source": "d_smart_reminder_system_backend_app_services_blob_storage_py", "target": "services_blob_storage_parse_conn_str", "relation": "contains", "confidence": "EXTRACTED", "source_file": "D:\\smart-reminder-system\\backend\\app\\services\\blob_storage.py", "source_location": "L14", "weight": 1.0}, {"source": "d_smart_reminder_system_backend_app_services_blob_storage_py", "target": "services_blob_storage_container_client", "relation": "contains", "confidence": "EXTRACTED", "source_file": "D:\\smart-reminder-system\\backend\\app\\services\\blob_storage.py", "source_location": "L24", "weight": 1.0}, {"source": "d_smart_reminder_system_backend_app_services_blob_storage_py", "target": "services_blob_storage_upload_audio", "relation": "contains", "confidence": "EXTRACTED", "source_file": "D:\\smart-reminder-system\\backend\\app\\services\\blob_storage.py", "source_location": "L31", "weight": 1.0}, {"source": "d_smart_reminder_system_backend_app_services_blob_storage_py", "target": "services_blob_storage_generate_sas_url", "relation": "contains", "confidence": "EXTRACTED", "source_file": "D:\\smart-reminder-system\\backend\\app\\services\\blob_storage.py", "source_location": "L41", "weight": 1.0}, {"source": "d_smart_reminder_system_backend_app_services_blob_storage_py", "target": "services_blob_storage_delete_audio", "relation": "contains", "confidence": "EXTRACTED", "source_file": "D:\\smart-reminder-system\\backend\\app\\services\\blob_storage.py", "source_location": "L62", "weight": 1.0}, {"source": "d_smart_reminder_system_backend_app_services_blob_storage_py", "target": "services_blob_storage_copy_audio", "relation": "contains", "confidence": "EXTRACTED", "source_file": "D:\\smart-reminder-system\\backend\\app\\services\\blob_storage.py", "source_location": "L69", "weight": 1.0}, {"source": "services_blob_storage_upload_audio", "target": "services_blob_storage_container_client", "relation": "calls", "context": "call", "confidence": "EXTRACTED", "source_file": "D:\\smart-reminder-system\\backend\\app\\services\\blob_storage.py", "source_location": "L33", "weight": 1.0}, {"source": "services_blob_storage_generate_sas_url", "target": "services_blob_storage_parse_conn_str", "relation": "calls", "context": "call", "confidence": "EXTRACTED", "source_file": "D:\\smart-reminder-system\\backend\\app\\services\\blob_storage.py", "source_location": "L44", "weight": 1.0}, {"source": "services_blob_storage_delete_audio", "target": "services_blob_storage_container_client", "relation": "calls", "context": "call", "confidence": "EXTRACTED", "source_file": "D:\\smart-reminder-system\\backend\\app\\services\\blob_storage.py", "source_location": "L64", "weight": 1.0}, {"source": "services_blob_storage_copy_audio", "target": "services_blob_storage_container_client", "relation": "calls", "context": "call", "confidence": "EXTRACTED", "source_file": "D:\\smart-reminder-system\\backend\\app\\services\\blob_storage.py", "source_location": "L71", "weight": 1.0}, {"source": "services_blob_storage_rationale_15", "target": "services_blob_storage_parse_conn_str", "relation": "rationale_for", "confidence": "EXTRACTED", "source_file": "D:\\smart-reminder-system\\backend\\app\\services\\blob_storage.py", "source_location": "L15", "weight": 1.0}, {"source": "services_blob_storage_rationale_32", "target": "services_blob_storage_upload_audio", "relation": "rationale_for", "confidence": "EXTRACTED", "source_file": "D:\\smart-reminder-system\\backend\\app\\services\\blob_storage.py", "source_location": "L32", "weight": 1.0}, {"source": "services_blob_storage_rationale_42", "target": "services_blob_storage_generate_sas_url", "relation": "rationale_for", "confidence": "EXTRACTED", "source_file": "D:\\smart-reminder-system\\backend\\app\\services\\blob_storage.py", "source_location": "L42", "weight": 1.0}, {"source": "services_blob_storage_rationale_70", "target": "services_blob_storage_copy_audio", "relation": "rationale_for", "confidence": "EXTRACTED", "source_file": "D:\\smart-reminder-system\\backend\\app\\services\\blob_storage.py", "source_location": "L70", "weight": 1.0}], "raw_calls": [{"caller_nid": "services_blob_storage_parse_conn_str", "callee": "split", "is_member_call": true, "source_file": "D:\\smart-reminder-system\\backend\\app\\services\\blob_storage.py", "source_location": "L17"}, {"caller_nid": "services_blob_storage_parse_conn_str", "callee": "partition", "is_member_call": true, "source_file": "D:\\smart-reminder-system\\backend\\app\\services\\blob_storage.py", "source_location": "L19"}, {"caller_nid": "services_blob_storage_container_client", "callee": "get_settings", "is_member_call": false, "source_file": "D:\\smart-reminder-system\\backend\\app\\services\\blob_storage.py", "source_location": "L25"}, {"caller_nid": "services_blob_storage_container_client", "callee": "get_container_client", "is_member_call": true, "source_file": "D:\\smart-reminder-system\\backend\\app\\services\\blob_storage.py", "source_location": "L26"}, {"caller_nid": "services_blob_storage_container_client", "callee": "from_connection_string", "is_member_call": true, "source_file": "D:\\smart-reminder-system\\backend\\app\\services\\blob_storage.py", "source_location": "L26"}, {"caller_nid": "services_blob_storage_upload_audio", "callee": "get_blob_client", "is_member_call": true, "source_file": "D:\\smart-reminder-system\\backend\\app\\services\\blob_storage.py", "source_location": "L33"}, {"caller_nid": "services_blob_storage_upload_audio", "callee": "upload_blob", "is_member_call": true, "source_file": "D:\\smart-reminder-system\\backend\\app\\services\\blob_storage.py", "source_location": "L34"}, {"caller_nid": "services_blob_storage_upload_audio", "callee": "ContentSettings", "is_member_call": false, "source_file": "D:\\smart-reminder-system\\backend\\app\\services\\blob_storage.py", "source_location": "L37"}, {"caller_nid": "services_blob_storage_generate_sas_url", "callee": "get_settings", "is_member_call": false, "source_file": "D:\\smart-reminder-system\\backend\\app\\services\\blob_storage.py", "source_location": "L43"}, {"caller_nid": "services_blob_storage_generate_sas_url", "callee": "generate_blob_sas", "is_member_call": false, "source_file": "D:\\smart-reminder-system\\backend\\app\\services\\blob_storage.py", "source_location": "L48"}, {"caller_nid": "services_blob_storage_generate_sas_url", "callee": "BlobSasPermissions", "is_member_call": false, "source_file": "D:\\smart-reminder-system\\backend\\app\\services\\blob_storage.py", "source_location": "L53"}, {"caller_nid": "services_blob_storage_generate_sas_url", "callee": "now", "is_member_call": true, "source_file": "D:\\smart-reminder-system\\backend\\app\\services\\blob_storage.py", "source_location": "L54"}, {"caller_nid": "services_blob_storage_generate_sas_url", "callee": "timedelta", "is_member_call": false, "source_file": "D:\\smart-reminder-system\\backend\\app\\services\\blob_storage.py", "source_location": "L54"}, {"caller_nid": "services_blob_storage_delete_audio", "callee": "delete_blob", "is_member_call": true, "source_file": "D:\\smart-reminder-system\\backend\\app\\services\\blob_storage.py", "source_location": "L64"}, {"caller_nid": "services_blob_storage_delete_audio", "callee": "get_blob_client", "is_member_call": true, "source_file": "D:\\smart-reminder-system\\backend\\app\\services\\blob_storage.py", "source_location": "L64"}, {"caller_nid": "services_blob_storage_delete_audio", "callee": "warning", "is_member_call": true, "source_file": "D:\\smart-reminder-system\\backend\\app\\services\\blob_storage.py", "source_location": "L66"}, {"caller_nid": "services_blob_storage_copy_audio", "callee": "get_blob_client", "is_member_call": true, "source_file": "D:\\smart-reminder-system\\backend\\app\\services\\blob_storage.py", "source_location": "L72"}, {"caller_nid": "services_blob_storage_copy_audio", "callee": "start_copy_from_url", "is_member_call": true, "source_file": "D:\\smart-reminder-system\\backend\\app\\services\\blob_storage.py", "source_location": "L73"}, {"caller_nid": "services_blob_storage_copy_audio", "callee": "get_blob_client", "is_member_call": true, "source_file": "D:\\smart-reminder-system\\backend\\app\\services\\blob_storage.py", "source_location": "L73"}]}